heartbreak_code/__init__.py
heartbreak_code/backup_dancer.py
heartbreak_code/chart_topper.py
heartbreak_code/choreography.py
heartbreak_code/dear_reader.py
heartbreak_code/deja_vu.py
heartbreak_code/eras.py
heartbreak_code/final_draft.py
heartbreak_code/greatest_hits.py
heartbreak_code/interpreter.py
heartbreak_code/music_video.py
heartbreak_code/narrative_arc.py
heartbreak_code/package_manager.py
heartbreak_code/parser.py
heartbreak_code/passing_notes.py
heartbreak_code/security_sandbox.py
heartbreak_code/storyboard.py
heartbreak_code/the_archives.py
heartbreak_code/the_setlist.py
heartbreak_code/tokenizer.py
heartbreak_code/unplugged_session.py
heartbreak_code/wasm_target.py
heartbreak_code-0.0.4.dist-info/METADATA
heartbreak_code-0.0.4.dist-info/WHEEL
heartbreak_code-0.0.4.dist-info/top_level.txt
heartbreak_code-0.0.4.dist-info/RECORD
