Metadata-Version: 2.4
Name: heartbreak-code
Version: 0.0.4
Summary: A Python project.
Author-email: Your Name <you@example.com>
Project-URL: Homepage, https://github.com/pypa/sampleproject
Project-URL: Bug Tracker, https://github.com/pypa/sampleproject/issues
Requires-Python: >=3.7
Requires-Dist: requests
Requires-Dist: argparse
Requires-Dist: watchdog
